kel/__init__.py
kel/cluster/__init__.py
kel/cluster/cluster.py
kel/cluster/components.py
kel/cluster/keykeeper.py
kel/cluster/providers/__init__.py
kel/cluster/providers/gce.py
kel_cluster-0.0.3.dist-info/DESCRIPTION.rst
kel_cluster-0.0.3.dist-info/METADATA
kel_cluster-0.0.3.dist-info/RECORD
kel_cluster-0.0.3.dist-info/WHEEL
kel_cluster-0.0.3.dist-info/metadata.json
kel_cluster-0.0.3.dist-info/top_level.txt
