Metadata-Version: 2.0
Name: kel-cluster
Version: 0.0.3
Summary: Kel cluster management library
Home-page: UNKNOWN
Author: Eldarion, Inc.
Author-email: development@eldarion.com
License: UNKNOWN
Platform: UNKNOWN
Requires-Dist: Jinja2
Requires-Dist: PyYAML
Requires-Dist: cryptography
Requires-Dist: google-api-python-client
Requires-Dist: pykube
